README.md
setup.py
gem5art/tasks/__init__.py
gem5art/tasks/celery.py
gem5art/tasks/tasks.py
gem5art_tasks.egg-info/PKG-INFO
gem5art_tasks.egg-info/SOURCES.txt
gem5art_tasks.egg-info/dependency_links.txt
gem5art_tasks.egg-info/requires.txt
gem5art_tasks.egg-info/top_level.txt