Metadata-Version: 2.1
Name: gem5art-tasks
Version: 0.3.0
Summary: A celery app for gem5art
Home-page: https://github.com/darchr/gem5art
Author: Davis Architecture Research Group (DArchR)
Author-email: jlowepower@ucdavis.edu
License: BSD
Project-URL: Bug Reports, https://github.com/darchr/gem5art/issues
Project-URL: Source, https://github.com/darchr/gem5art
Project-URL: Documentation, https://gem5art.readthedocs.io/en/latest/
Keywords: simulation architecture gem5
Platform: UNKNOWN
Classifier: Development Status :: 3 - Alpha
Classifier: License :: OSI Approved :: BSD License
Classifier: Topic :: System :: Hardware
Classifier: Intended Audience :: Science/Research
Classifier: Programming Language :: Python :: 3
Requires-Python: >=3.6
Provides-Extra: flower
